[
    {
        "id": 1,
        "type": "cat",
        "name": "Skarin",
        "age": 12,
        "bio": "'Tubby kitty at heart'",
        "pic": "/Skarin.jpg"
    },
    {
        "id": 2,
        "type": "cat",
        "name": "Tiger",
        "age": 12,
        "bio": "'Killer kittay'",
        "pic": "/Tiger.jpg"
    },
    {
        "id": 3,
        "type": "dog",
        "name": "Tripp",
        "age": 8,
        "bio": "'Pee attack'",
        "pic": "/Tripp.jpg"
    },
    {
        "id": 4,
        "type": "dog",
        "name": "Harley",
        "age": 7,
        "bio": "'What a bitch'",
        "pic": "/Harley.jpg"
    },
    {
        "id": 5,
        "type": "soon",
        "pic": "/soondog.jpg"
    },
    {
        "id": 6,
        "type": "soon",
        "pic": "/sooncat.jpg"
    }
]